pyeasypay/__init__.py
pyeasypay/core/__init__.py
pyeasypay/core/pay.py
pyeasypay/core/providers/__init__.py
pyeasypay/core/providers/aaio.py
pyeasypay/core/providers/cryptobot.py
pyeasypay/core/providers/crystalpay.py
pyeasypay-0.2.10.dist-info/LICENSE
pyeasypay-0.2.10.dist-info/METADATA
pyeasypay-0.2.10.dist-info/WHEEL
pyeasypay-0.2.10.dist-info/top_level.txt
pyeasypay-0.2.10.dist-info/RECORD
