Metadata-Version: 2.1
Name: pyeasypay
Version: 0.2.10
Summary: Make money from your Python projects the easy way.
Home-page: https://github.com/nichind/pyeasypay
Author: nichind
Author-email: nichinddev@gmail.com
Classifier: Programming Language :: Python :: 3.11
Classifier: License :: OSI Approved :: MIT License
Classifier: Operating System :: OS Independent
Requires-Python: >=3.8
License-File: LICENSE
Requires-Dist: aiohttp
Requires-Dist: python-dotenv
Requires-Dist: aiocryptopay
Requires-Dist: requests
Requires-Dist: sqlalchemy
